optunizer/__init__.py
optunizer/__main__.py
optunizer/app.py
optunizer/factory.py
optunizer/optimizer.py
optunizer-0.1.17.dist-info/LICENSE
optunizer-0.1.17.dist-info/METADATA
optunizer-0.1.17.dist-info/WHEEL
optunizer-0.1.17.dist-info/top_level.txt
optunizer-0.1.17.dist-info/RECORD
