Metadata-Version: 2.1
Name: optunizer
Version: 0.1.17
Summary: Optuna extension for JSON and YAML configuration files
Home-page: https://github.com/romanzes637/optunizer
Author: Roman Pashkovsky
Author-email: romapasky@gmail.com
Project-URL: Bug Tracker, https://github.com/romanzes637/optunizer/issues
Classifier: Programming Language :: Python :: 3
Classifier: License :: OSI Approved :: MIT License
Classifier: Operating System :: OS Independent
Requires-Python: >=3.6
License-File: LICENSE
Requires-Dist: optuna
Requires-Dist: python-dotenv
Requires-Dist: pyyaml
Provides-Extra: psycopg
Requires-Dist: psycopg2 ; extra == 'psycopg'
Provides-Extra: viz
Requires-Dist: streamlit ; extra == 'viz'
Requires-Dist: plotly ; extra == 'viz'
